integrations/__init__.py
integrations/cli_wrappers/amp/amp.py
integrations/cli_wrappers/claude_code/claude_wrapper_v3.py
integrations/cli_wrappers/claude_code/format_utils.py
integrations/cli_wrappers/claude_code/session_reset_handler.py
integrations/cli_wrappers/codex/codex-cli/scripts/build_npm_package.py
integrations/cli_wrappers/codex/codex-cli/scripts/install_native_deps.py
integrations/cli_wrappers/codex/codex-rs/mcp-types/check_lib_rs.py
integrations/cli_wrappers/codex/codex-rs/mcp-types/generate_mcp_types.py
integrations/cli_wrappers/codex/scripts/asciicheck.py
integrations/cli_wrappers/codex/scripts/readme_toc.py
integrations/headless/__init__.py
integrations/headless/claude_code.py
integrations/utils/__init__.py
integrations/utils/git_utils.py
integrations/webhooks/claude_code/claude_code.py
omnara/__init__.py
omnara/cli.py
omnara/_bin/README.md
omnara/_bin/codex/linux-x64/codex
omnara/agents/codex.py
omnara/sdk/__init__.py
omnara/sdk/async_client.py
omnara/sdk/client.py
omnara/sdk/exceptions.py
omnara/sdk/models.py
omnara/sdk/utils.py
omnara.libs/libcrypto-bdaed0ea.so.1.1.1k
omnara.libs/libssl-60250281.so.1.1.1k
servers/mcp/__init__.py
servers/mcp/descriptions.py
servers/mcp/models.py
servers/mcp/server.py
servers/mcp/stdio_server.py
servers/mcp/tools.py
servers/mcp/utils.py
servers/shared/__init__.py
servers/shared/notification_base.py
servers/shared/notification_utils.py
servers/shared/notifications.py
servers/shared/twilio_service.py
servers/shared/db/__init__.py
servers/shared/db/queries.py
servers/shared/models/__init__.py
servers/shared/models/base.py
omnara-1.6.20.dist-info/METADATA
omnara-1.6.20.dist-info/WHEEL
omnara-1.6.20.dist-info/entry_points.txt
omnara-1.6.20.dist-info/top_level.txt
omnara-1.6.20.dist-info/RECORD
omnara-1.6.20.dist-info/licenses/LICENSE
