Metadata-Version: 2.4
Name: omnara
Version: 1.6.20
Summary: Omnara Agent Dashboard - MCP Server and Python SDK
Author-email: Omnara <ishaan@omnara.com>
License:                                  Apache License
Project-URL: Homepage, https://github.com/omnara-ai/omnara
Project-URL: Repository, https://github.com/omnara-ai/omnara
Project-URL: Issues, https://github.com/omnara-ai/omnara/issues
Keywords: mcp,ai,agents,dashboard,human-in-the-loop,claude-code
Classifier: Development Status :: 4 - Beta
Classifier: Intended Audience :: Developers
Classifier: Programming Language :: Python :: 3
Classifier: Programming Language :: Python :: 3.10
Classifier: Programming Language :: Python :: 3.11
Classifier: Programming Language :: Python :: 3.12
Requires-Python: >=3.10
License-File: LICENSE
Requires-Dist: requests>=2.25.0
Requires-Dist: urllib3>=1.26.0
Requires-Dist: aiohttp>=3.8.0
Requires-Dist: certifi>=2020.6.20
Requires-Dist: fastmcp>=2.9.2
Requires-Dist: fastapi>=0.100.0
Requires-Dist: uvicorn>=0.20.0
Requires-Dist: pydantic>=2.0.0
Requires-Dist: claude-code-sdk>=0.0.20
Dynamic: license-file
